[
  {
    "model": "catalog.ClassProduct",
    "pk": 1,
    "fields": {
      "name": "Halal"
    }
  },
  {
    "model": "catalog.ClassProduct",
    "pk": 2,
    "fields": {
      "name": "Kosher"
    }
  },
   {
    "model": "catalog.ClassProduct",
    "pk": 3,
    "fields": {
      "name": "Vegetarian"
    }
  },
  {
    "model": "catalog.ClassProduct",
    "pk": 4,
    "fields": {
      "name": "Vegan"
    }
  },
  {
    "model": "catalog.ClassProduct",
    "pk": 5,
    "fields": {
      "name": "BIO"
    }
  },
  {
    "model": "catalog.ClassProduct",
    "pk": 6,
    "fields": {
      "name": "Lactose Free"
    }
  },
  {
    "model": "catalog.ClassProduct",
    "pk": 7,
    "fields": {
      "name": "Gluten Free"
    }
  },
  {
    "model": "catalog.ClassProduct",
    "pk": 8,
    "fields": {
      "name": "Allergen Free"
    }
  }
]